crawlo/__init__.py
crawlo/__version__.py
crawlo/cli.py
crawlo/config.py
crawlo/config_validator.py
crawlo/crawler.py
crawlo/event.py
crawlo/exceptions.py
crawlo/framework.py
crawlo/interfaces.py
crawlo/mode_manager.py
crawlo/project.py
crawlo/stats_collector.py
crawlo/subscriber.py
crawlo/task_manager.py
crawlo/commands/__init__.py
crawlo/commands/check.py
crawlo/commands/genspider.py
crawlo/commands/help.py
crawlo/commands/list.py
crawlo/commands/run.py
crawlo/commands/schedule.py
crawlo/commands/startproject.py
crawlo/commands/stats.py
crawlo/commands/utils.py
crawlo/core/__init__.py
crawlo/core/engine.py
crawlo/core/processor.py
crawlo/core/scheduler.py
crawlo/data/__init__.py
crawlo/data/user_agents.py
crawlo/downloader/__init__.py
crawlo/downloader/aiohttp_downloader.py
crawlo/downloader/cffi_downloader.py
crawlo/downloader/httpx_downloader.py
crawlo/downloader/hybrid_downloader.py
crawlo/downloader/playwright_downloader.py
crawlo/downloader/selenium_downloader.py
crawlo/extension/__init__.py
crawlo/extension/health_check.py
crawlo/extension/log_interval.py
crawlo/extension/log_stats.py
crawlo/extension/logging_extension.py
crawlo/extension/memory_monitor.py
crawlo/extension/mysql_monitor.py
crawlo/extension/performance_profiler.py
crawlo/extension/redis_monitor.py
crawlo/extension/request_recorder.py
crawlo/factories/__init__.py
crawlo/factories/base.py
crawlo/factories/crawler.py
crawlo/factories/registry.py
crawlo/factories/utils.py
crawlo/filters/__init__.py
crawlo/filters/aioredis_filter.py
crawlo/filters/memory_filter.py
crawlo/initialization/__init__.py
crawlo/initialization/built_in.py
crawlo/initialization/context.py
crawlo/initialization/core.py
crawlo/initialization/phases.py
crawlo/initialization/registry.py
crawlo/initialization/utils.py
crawlo/items/__init__.py
crawlo/items/base.py
crawlo/items/fields.py
crawlo/items/items.py
crawlo/logging/__init__.py
crawlo/logging/config.py
crawlo/logging/factory.py
crawlo/logging/manager.py
crawlo-1.5.6.dist-info/METADATA
crawlo-1.5.6.dist-info/WHEEL
crawlo-1.5.6.dist-info/entry_points.txt
crawlo-1.5.6.dist-info/top_level.txt
crawlo-1.5.6.dist-info/RECORD
