Metadata-Version: 2.4
Name: crawlo
Version: 1.5.6
Summary: Crawlo: A high-performance asynchronous Python web crawling framework with distributed support.。
Home-page: https://github.com/crawl-coder/Crawlo.git
Author: crawl-coder
Author-email: crawlo@qq.com
License: MIT
Classifier: Programming Language :: Python :: 3
Classifier: License :: OSI Approved :: MIT License
Classifier: Operating System :: OS Independent
Requires-Python: >=3.6
Requires-Dist: aiohttp>=3.12.14
Requires-Dist: aiomysql>=0.2.0
Requires-Dist: aioredis>=2.0.1
Requires-Dist: asyncmy>=0.2.10
Requires-Dist: cssselect>=1.2.0
Requires-Dist: dateparser>=1.2.2
Requires-Dist: httpx[http2]>=0.27.0
Requires-Dist: curl-cffi>=0.13.0
Requires-Dist: lxml>=5.2.1
Requires-Dist: motor>=3.7.0
Requires-Dist: parsel>=1.9.1
Requires-Dist: pydantic>=2.11.7
Requires-Dist: pymongo>=4.11
Requires-Dist: PyMySQL>=1.1.1
Requires-Dist: python-dateutil>=2.9.0.post0
Requires-Dist: redis>=6.2.0
Requires-Dist: requests>=2.32.4
Requires-Dist: six>=1.17.0
Requires-Dist: ujson>=5.9.0
Requires-Dist: urllib3>=2.5.0
Requires-Dist: w3lib>=2.1.2
Requires-Dist: rich>=14.1.0
Requires-Dist: astor>=0.8.1
Requires-Dist: watchdog>=6.0.0
Provides-Extra: render
Requires-Dist: webdriver-manager>=4.0.0; extra == "render"
Requires-Dist: playwright; extra == "render"
Requires-Dist: selenium>=3.141.0; extra == "render"
Provides-Extra: all
Requires-Dist: bitarray>=1.5.3; extra == "all"
Requires-Dist: PyExecJS>=1.5.1; extra == "all"
Requires-Dist: pymongo>=3.10.1; extra == "all"
Requires-Dist: redis-py-cluster>=2.1.0; extra == "all"
Requires-Dist: webdriver-manager>=4.0.0; extra == "all"
Requires-Dist: playwright; extra == "all"
Requires-Dist: selenium>=3.141.0; extra == "all"
